__init__.py
__main__.py
profitmart.py
setup.py
utils.py
profitmart.egg-info/PKG-INFO
profitmart.egg-info/SOURCES.txt
profitmart.egg-info/dependency_links.txt
profitmart.egg-info/entry_points.txt
profitmart.egg-info/requires.txt
profitmart.egg-info/top_level.txt